{"cameraMode":{"drawMode":0,"name":"Shaded","section":"Shading Mode"},"sceneLighting":true,"audioPlay":false,"sceneViewState":{"m_AlwaysRefresh":false,"showFog":true,"showSkybox":true,"showFlares":true,"showImageEffects":true,"showParticleSystems":true,"showVisualEffectGraphs":true,"m_FxEnabled":true},"in2DMode":false,"pivot":{"x":-0.780855655670166,"y":-0.07062959671020508,"z":-1.3077305555343629},"rotation":{"x":0.6881123781204224,"y":0.021751834079623224,"z":-0.020646734163165094,"w":0.7249862551689148},"size":10.52703857421875,"orthographic":false}